_pyots.cpython-311-darwin.so
pyots/__init__.py
pyots-9.2.0.post2.dist-info/RECORD
pyots-9.2.0.post2.dist-info/LICENSE
pyots-9.2.0.post2.dist-info/WHEEL
pyots-9.2.0.post2.dist-info/top_level.txt
pyots-9.2.0.post2.dist-info/METADATA
