Metadata-Version: 2.1
Name: pyots
Version: 9.2.0.post2
Summary: Python wrapper for ot-sanitizer
Home-page: https://github.com/adobe-type-tools/pyots
Author: Adobe Type team & friends
Author-email: afdko@adobe.com
Classifier: Development Status :: 4 - Beta
Classifier: Intended Audience :: Developers
Classifier: Topic :: Software Development :: Testing
Classifier: License :: OSI Approved :: BSD License
Classifier: Programming Language :: Python :: 3.9
Classifier: Programming Language :: Python :: 3.10
Classifier: Programming Language :: Python :: 3.11
Classifier: Programming Language :: Python :: 3.12
Classifier: Operating System :: MacOS :: MacOS X
Classifier: Operating System :: POSIX :: Linux
Requires-Python: >=3.9
License-File: LICENSE
